key_pressed_count/keycount.py
key_pressed_count-1.0.0.1.dist-info/LICENSE
key_pressed_count-1.0.0.1.dist-info/METADATA
key_pressed_count-1.0.0.1.dist-info/WHEEL
key_pressed_count-1.0.0.1.dist-info/entry_points.txt
key_pressed_count-1.0.0.1.dist-info/top_level.txt
key_pressed_count-1.0.0.1.dist-info/RECORD
