Metadata-Version: 2.1
Name: key-pressed-count
Version: 1.0.0.1
Summary: A Python package which will count your all keypressed and mouse touch
Home-page: https://github.com/Vijayraj72/keylogger-app
Author: vijay saw
Author-email: imvijayraj72@gmail.com
License: MIT
Keywords: keypress count,mouse event,keyboard event,mouse key press,key press,keyboard and mouse event
Platform: UNKNOWN
Classifier: License :: OSI Approved :: MIT License
Classifier: Programming Language :: Python :: 3
Classifier: Programming Language :: Python :: 3.7
Requires-Dist: Xlib
Requires-Dist: pyxhook
